[
  {
    "title": "Completează sondaje de opinie cu PulseOpinion!",
    "link": "https://singingfiles.com/show.php?l=0&u=2455756&id=72464"
  },
  {
    "title": "Vezi cum poți obține un ceas inteligent acum!",
    "link": "https://singingfiles.com/show.php?l=0&u=2455756&id=72111"
  },
  {
    "title": "Poți deveni milionar!",
    "link": "https://singingfiles.com/show.php?l=0&u=2455756&id=54834"
  },
  {
    "title": "Înscrie-te pentru cel mai recent ceas inteligent!",
    "link": "https://singingfiles.com/show.php?l=0&u=2455756&id=72109"
  },
  {
    "title": "Completează acum cel mai recent sondaj de opinie!",
    "link": "https://singingfiles.com/show.php?l=0&u=2455756&id=72462"
  },
  {
    "title": "Completează sondaje de opinie cu PulseOpinion!",
    "link": "https://singingfiles.com/show.php?l=0&u=2455756&id=72463"
  }
]
